ak_websockify-0.6.0.1.data/data/share/websockify/include/base64.js
ak_websockify-0.6.0.1.data/data/share/websockify/include/util.js
ak_websockify-0.6.0.1.data/data/share/websockify/include/websock.js
ak_websockify-0.6.0.1.data/data/share/websockify/include/web-socket-js/swfobject.js
ak_websockify-0.6.0.1.data/data/share/websockify/include/web-socket-js/web_socket.js
ak_websockify-0.6.0.1.data/data/share/websockify/include/web-socket-js/WebSocketMain.swf
ak_websockify-0.6.0.1.dist-info/DESCRIPTION.rst
ak_websockify-0.6.0.1.dist-info/entry_points.txt
ak_websockify-0.6.0.1.dist-info/METADATA
ak_websockify-0.6.0.1.dist-info/metadata.json
ak_websockify-0.6.0.1.dist-info/RECORD
ak_websockify-0.6.0.1.dist-info/top_level.txt
ak_websockify-0.6.0.1.dist-info/WHEEL
websockify/__init__.py
websockify/websocket.py
websockify/websocketproxy.py
