Metadata-Version: 2.0
Name: ak-websockify
Version: 0.6.0.1
Summary: Appknox forn of Websockify.
Home-page: https://github.com/kanaka/websockify
Author: Joel Martin
Author-email: github@martintribe.org
License: LGPLv3
Keywords: noVNC websockify
Platform: UNKNOWN
Classifier: Programming Language :: Python
Classifier: Development Status :: 3 - Alpha
Classifier: Intended Audience :: Developers
Classifier: Topic :: Software Development :: Build Tools
Classifier: License :: OSI Approved :: MIT License
Classifier: Programming Language :: Python :: 3
Classifier: Programming Language :: Python :: 3.5
Requires-Dist: numpy
